pyXGTClient/__init__.py
pyXGTClient/client.py
pyXGTClient/constants.py
pyXGTClient/utils.py
pyXGTClient-0.0.1.dist-info/METADATA
pyXGTClient-0.0.1.dist-info/WHEEL
pyXGTClient-0.0.1.dist-info/top_level.txt
pyXGTClient-0.0.1.dist-info/RECORD
