Metadata-Version: 2.1
Name: pyXGTClient
Version: 0.0.1
Summary: A simple XGT Client library for Python
Home-page: 
Author: Choi Woo Chang
Author-email: uchang2@gmail.com
License: MIT
Platform: any
